matflow/__init__.py
matflow/__pyinstaller/__init__.py
matflow/__pyinstaller/hook-matflow.py
matflow/_version.py
matflow/cli.py
matflow/data/demo_data_manifest/__init__.py
matflow/data/demo_data_manifest/demo_data_manifest.json
matflow/data/scripts/__init__.py
matflow/data/scripts/damask/__init__.py
matflow/data/scripts/damask/add_VE_buffer_zones.py
matflow/data/scripts/damask/dump_all_yield_stresses.py
matflow/data/scripts/damask/extract_damask_HDF5.py
matflow/data/scripts/damask/generate_volume_element_extrusion.py
matflow/data/scripts/damask/generate_volume_element_from_damask_input_files.py
matflow/data/scripts/damask/generate_volume_element_voronoi.py
matflow/data/scripts/damask/generate_volume_element_voronoi_variates.py
matflow/data/scripts/damask/get_yield_stress.py
matflow/data/scripts/damask/high_concurrency/process_HDF5.py
matflow/data/scripts/damask/high_concurrency/write_input_files.py
matflow/data/scripts/damask/modify_VE_grid_size.py
matflow/data/scripts/damask/process_damask_HDF5.py
matflow/data/scripts/damask/read_log.py
matflow/data/scripts/damask/seeds_from_random.py
matflow/data/scripts/damask/viz_damask_HDF5.py
matflow/data/scripts/damask/write_geom.py
matflow/data/scripts/damask/write_load.py
matflow/data/scripts/damask/write_material.py
matflow/data/scripts/damask/write_numerics.py
matflow/data/scripts/defdap/__init__.py
matflow/data/scripts/defdap/load_microstructure_EBSD.py
matflow/data/scripts/defdap/load_microstructure_EBSD_DIC.py
matflow/data/scripts/demo_script_action.py
matflow/data/scripts/dream_3D/__init__.py
matflow/data/scripts/dream_3D/generate_volume_element_statistics.py
matflow/data/scripts/dream_3D/parse_dream_3D_volume_element.py
matflow/data/scripts/dump_group_data.py
matflow/data/scripts/formable/__init__.py
matflow/data/scripts/formable/fit_single_crystal_parameters.py
matflow/data/scripts/formable/fit_yield_function.py
matflow/data/scripts/formable/read_tensile_test_CSV.py
matflow/data/scripts/import_VE.py
matflow_new-0.3.0a200.dist-info/LICENSE
matflow_new-0.3.0a200.dist-info/METADATA
matflow_new-0.3.0a200.dist-info/WHEEL
matflow_new-0.3.0a200.dist-info/entry_points.txt
matflow_new-0.3.0a200.dist-info/RECORD
