Metadata-Version: 2.3
Name: matflow-new
Version: 0.3.0a200
Summary: Computational workflows for materials science
License: MIT
Author: aplowman
Author-email: adam.plowman@manchester.ac.uk
Requires-Python: >=3.9,<3.14
Classifier: License :: OSI Approved :: MIT License
Classifier: Programming Language :: Python :: 3
Classifier: Programming Language :: Python :: 3.9
Classifier: Programming Language :: Python :: 3.10
Classifier: Programming Language :: Python :: 3.11
Classifier: Programming Language :: Python :: 3.12
Classifier: Programming Language :: Python :: 3.13
Provides-Extra: test
Requires-Dist: hpcflow-new2 (==0.2.0a268)
Requires-Dist: matplotlib (>=3.7,<4.0)
Requires-Dist: numpy (>=1.26.4,<2.0.0) ; python_version < "3.13"
Requires-Dist: numpy (>=2.2.4,<3.0.0) ; python_version >= "3.13"
Requires-Dist: pytest (>=7.2.0,<8.0.0) ; extra == "test"
Requires-Dist: skops (>=0.13.0,<0.14.0)
Requires-Dist: typing-extensions (>=4.12.2,<5.0.0)
